{
  "timestamp": "20251109_014254",
  "error_rate_sweep": [
    {
      "error_rate": 0.0,
      "temperature_gradient": 1.4700268398976961,
      "total_entropy": 22.55925574643018,
      "demon_accuracy": 1.0,
      "bits_processed": 1082.0
    },
    {
      "error_rate": 0.05,
      "temperature_gradient": 1.3584515417315812,
      "total_entropy": 22.745059035404182,
      "demon_accuracy": 0.9496336996336996,
      "bits_processed": 1092.0
    },
    {
      "error_rate": 0.1,
      "temperature_gradient": 1.0779626008576415,
      "total_entropy": 23.412232091691315,
      "demon_accuracy": 0.8963963963963963,
      "bits_processed": 1110.0
    },
    {
      "error_rate": 0.2,
      "temperature_gradient": 0.6037492143131796,
      "total_entropy": 27.376258698730418,
      "demon_accuracy": 0.7869731800766283,
      "bits_processed": 1305.0
    },
    {
      "error_rate": 0.3,
      "temperature_gradient": 0.9609636155999863,
      "total_entropy": 23.263381395658516,
      "demon_accuracy": 0.7002700270027002,
      "bits_processed": 1111.0
    },
    {
      "error_rate": 0.5,
      "temperature_gradient": -0.25924526284980787,
      "total_entropy": 23.289315354091656,
      "demon_accuracy": 0.49216589861751153,
      "bits_processed": 1085.0
    }
  ],
  "memory_cost_sweep": [
    {
      "memory_cost": 0.0,
      "temperature_gradient": 1.4126496231388277,
      "total_entropy": 1.1407172988428362,
      "demon_entropy_cost": 0.0,
      "bits_processed": 1151.0
    },
    {
      "memory_cost": 0.001,
      "temperature_gradient": 1.5282320810127543,
      "total_entropy": 3.493546255631141,
      "demon_entropy_cost": 2.2909999999999298,
      "bits_processed": 1151.0
    },
    {
      "memory_cost": 0.01,
      "temperature_gradient": 1.259827659308715,
      "total_entropy": 21.18935728978129,
      "demon_entropy_cost": 20.080000000000158,
      "bits_processed": 1008.0
    },
    {
      "memory_cost": 0.05,
      "temperature_gradient": 1.2418632130775498,
      "total_entropy": 111.6491621537103,
      "demon_entropy_cost": 110.5999999999979,
      "bits_processed": 1112.0
    },
    {
      "memory_cost": 0.1,
      "temperature_gradient": 1.09896873869263,
      "total_entropy": 222.1750550495504,
      "demon_entropy_cost": 221.1999999999958,
      "bits_processed": 1112.0
    },
    {
      "memory_cost": 0.5,
      "temperature_gradient": 1.6769653708135137,
      "total_entropy": 1103.1117405980967,
      "demon_entropy_cost": 1102.0,
      "bits_processed": 1104.0
    }
  ],
  "capacity_sweep": [
    {
      "capacity": 1.0,
      "temperature_gradient": 1.3294212037439264,
      "total_entropy": 15.238361227361715,
      "bits_processed": 710.0
    },
    {
      "capacity": 5.0,
      "temperature_gradient": 1.1627848208587817,
      "total_entropy": 21.676277279403223,
      "bits_processed": 1033.0
    },
    {
      "capacity": 10.0,
      "temperature_gradient": 1.1851067290308621,
      "total_entropy": 23.512271217609598,
      "bits_processed": 1128.0
    },
    {
      "capacity": 20.0,
      "temperature_gradient": 1.162608804606815,
      "total_entropy": 26.181479783101068,
      "bits_processed": 1241.0
    },
    {
      "capacity": 50.0,
      "temperature_gradient": 0.9726596245364355,
      "total_entropy": 21.398570552458132,
      "bits_processed": 1044.0
    },
    {
      "capacity": 100.0,
      "temperature_gradient": 1.4587602435391784,
      "total_entropy": 24.208170201643952,
      "bits_processed": 1195.0
    }
  ]
}